quantuiti/__about__.py
quantuiti/__init__.py
quantuiti/__main__.py
quantuiti/_algorithm.py
quantuiti/_buildPython.py
quantuiti/_cci.py
quantuiti/_ema.py
quantuiti/_emv.py
quantuiti/_graph.py
quantuiti/_roc.py
quantuiti/_sma.py
quantuiti/template.txt
quantuiti-0.1.1.dist-info/LICENSE
quantuiti-0.1.1.dist-info/METADATA
quantuiti-0.1.1.dist-info/WHEEL
quantuiti-0.1.1.dist-info/entry_points.txt
quantuiti-0.1.1.dist-info/top_level.txt
quantuiti-0.1.1.dist-info/RECORD
