Metadata-Version: 2.1
Name: quantuiti
Version: 0.1.1
Summary: quantuiti library for quantitative finance
Home-page: https://github.com/quantuiti/python-quantuiti
Author: Dylan Muraco
Author-email: dylanjmuraco@gmail.com
License: UNKNOWN
Project-URL: Bug Tracker, https://github.com/quantuiti/python-quantuiti/issues
Platform: UNKNOWN
Classifier: Programming Language :: Python :: 3
Classifier: License :: OSI Approved :: MIT License
Classifier: Operating System :: OS Independent
Requires-Python: >=3.6
